historical_api/__init__.py
historical_api/alembic.ini
historical_api/api/__init__.py
historical_api/api/v1/__init__.py
historical_api/api/v1/circuit/__init__.py
historical_api/api/v1/circuit/models.py
historical_api/api/v1/circuit/services.py
historical_api/api/v1/circuit/views.py
historical_api/api/v1/country/__init__.py
historical_api/api/v1/country/models.py
historical_api/api/v1/country/services.py
historical_api/api/v1/driver/__init__.py
historical_api/api/v1/driver/models.py
historical_api/api/v1/driver/services.py
historical_api/api/v1/driver/views.py
historical_api/api/v1/event/__init__.py
historical_api/api/v1/event/enums.py
historical_api/api/v1/event/models.py
historical_api/api/v1/event/services.py
historical_api/api/v1/event/views.py
historical_api/api/v1/event_role/enums.py
historical_api/api/v1/event_role/models.py
historical_api/api/v1/event_role/services.py
historical_api/api/v1/location/__init__.py
historical_api/api/v1/location/models.py
historical_api/api/v1/location/services.py
historical_api/api/v1/meeting/__init__.py
historical_api/api/v1/meeting/models.py
historical_api/api/v1/meeting/services.py
historical_api/api/v1/meeting/views.py
historical_api/api/v1/pit/__init__.py
historical_api/api/v1/pit/models.py
historical_api/api/v1/pit/services.py
historical_api/api/v1/race_control/__init__.py
historical_api/api/v1/race_control/models.py
historical_api/api/v1/race_control/services.py
historical_api/api/v1/session/__init__.py
historical_api/api/v1/session/models.py
historical_api/api/v1/session/services.py
historical_api/api/v1/session/views.py
historical_api/api/v1/team/__init__.py
historical_api/api/v1/team/models.py
historical_api/api/v1/team/services.py
historical_api/api/v1/team/views.py
historical_api/api/v1/turn/__init__.py
historical_api/api/v1/turn/models.py
historical_api/api/v1/turn/services.py
historical_api/core/__init__.py
historical_api/core/db.py
historical_api/core/models.py
historical_api/main.py
historical_api-0.0.1.dist-info/WHEEL
historical_api-0.0.1.dist-info/METADATA
historical_api-0.0.1.dist-info/RECORD
